django_xinclude/__init__.py
django_xinclude/apps.py
django_xinclude/cache.py
django_xinclude/checks.py
django_xinclude/conf.py
django_xinclude/exceptions.py
django_xinclude/logger.py
django_xinclude/urls.py
django_xinclude/views.py
django_xinclude/templates/django_xinclude/include.html
django_xinclude/templatetags/__init__.py
django_xinclude/templatetags/xinclude.py
django_xinclude-0.1.1.dist-info/LICENSE
django_xinclude-0.1.1.dist-info/WHEEL
django_xinclude-0.1.1.dist-info/METADATA
django_xinclude-0.1.1.dist-info/RECORD
