Metadata-Version: 2.1
Name: django-xinclude
Version: 0.1.1
Summary: django-xinclude
Keywords: django,templates,htmx,xhr,cache
Author-email: Giannis Terzopoulos <terzo.giannis@gmail.com>
Requires-Python: >=3.10
Classifier: Development Status :: 1 - Planning
Classifier: Intended Audience :: Developers
Classifier: License :: OSI Approved :: MIT License
Classifier: Operating System :: OS Independent
Classifier: Framework :: Django
Classifier: Framework :: Django :: 4.2
Classifier: Framework :: Django :: 5.0
Classifier: Programming Language :: Python :: 3 :: Only
Classifier: Programming Language :: Python :: 3.10
Classifier: Programming Language :: Python :: 3.11
Classifier: Programming Language :: Python :: 3.12
Classifier: Typing :: Typed
Requires-Dist: Django>=4.2
Requires-Dist: django-stubs[compatible-mypy] ; extra == "dev"
Requires-Dist: ipython ; extra == "dev"
Requires-Dist: ruff ; extra == "dev"
Requires-Dist: pytest ; extra == "tests"
Requires-Dist: pytest-django ; extra == "tests"
Requires-Dist: coverage ; extra == "tests"
Project-URL: Changelog, https://github.com/g-nie/django-xinclude/blob/main/CHANGELOG.rst
Project-URL: Repository, https://github.com/g-nie/django-xinclude
Provides-Extra: dev
Provides-Extra: tests
